scraper.py
blingbyscraper/__init__.py
blingbyscraper/scraper.py
BlingbyImageScraper-0.1.0.dist-info/LICENSE.txt
BlingbyImageScraper-0.1.0.dist-info/METADATA
BlingbyImageScraper-0.1.0.dist-info/WHEEL
BlingbyImageScraper-0.1.0.dist-info/top_level.txt
BlingbyImageScraper-0.1.0.dist-info/RECORD
